influxdb_bundle/__init__.py
influxdb_bundle/bundle.py
influxdb_bundle-1.0.dist-info/LICENSE
influxdb_bundle-1.0.dist-info/METADATA
influxdb_bundle-1.0.dist-info/WHEEL
influxdb_bundle-1.0.dist-info/top_level.txt
influxdb_bundle-1.0.dist-info/RECORD
